pubmedAuthorAffiliation/__init__.py
pubmedAuthorAffiliation/pubmedAuthorAffiliation.py
pubmedAuthorAffiliation/test_pubmedAuthorAffiliation.py
pubmed_author_affiliation-0.3.data/data/example_input_data/README.rst
pubmed_author_affiliation-0.3.data/data/example_input_data/emdb-2010-4.txt
pubmed_author_affiliation-0.3.data/data/example_input_data/emdb-2010.txt
pubmed_author_affiliation-0.3.data/data/example_input_data/emdb-2011-4.txt
pubmed_author_affiliation-0.3.data/data/example_input_data/emdb-2011.txt
pubmed_author_affiliation-0.3.data/data/example_input_data/emdb-2012-4.txt
pubmed_author_affiliation-0.3.data/data/example_input_data/emdb-2012.txt
pubmed_author_affiliation-0.3.data/data/example_input_data/emdb-2013-4.txt
pubmed_author_affiliation-0.3.data/data/example_input_data/emdb-2013.txt
pubmed_author_affiliation-0.3.data/data/example_input_data/emdb-2014-4.txt
pubmed_author_affiliation-0.3.data/data/example_input_data/emdb-2014.txt
pubmed_author_affiliation-0.3.data/data/example_input_data/emdb-2015-4.txt
pubmed_author_affiliation-0.3.data/data/example_input_data/emdb-2015.txt
pubmed_author_affiliation-0.3.data/data/example_input_data/emdb-2016-4.txt
pubmed_author_affiliation-0.3.data/data/example_input_data/emdb-2016.txt
pubmed_author_affiliation-0.3.dist-info/METADATA
pubmed_author_affiliation-0.3.dist-info/RECORD
pubmed_author_affiliation-0.3.dist-info/WHEEL
pubmed_author_affiliation-0.3.dist-info/top_level.txt
