Metadata-Version: 2.1
Name: pubmed-author-affiliation
Version: 0.3
Summary: Search for author affiliations from Pubmed for a list of Pubmed IDs and DOIs
Home-page: https://github.com/emdb-empiar/pubmed-author-affiliations
Author: Ardan Patwardhan
Author-email: ardan@ebi.ac.uk
License: Apache 2
Platform: UNKNOWN
